README
setup.py
./dedist/__init__.py
./dedist/dedist.py
DeDist.egg-info/PKG-INFO
DeDist.egg-info/SOURCES.txt
DeDist.egg-info/dependency_links.txt
DeDist.egg-info/top_level.txt