Metadata-Version: 1.1
Name: DeDist
Version: 0.1
Summary: A Python library for estimating decoding distributions
Home-page: https://github.com/swkeemink/DeDist
Author: Sander Keemink
Author-email: swkeemink@scimail.eu
License: GNU
Download-URL: https://github.com/swkeemink/DeDist/archive/0.1.tar.gz
Platform: UNKNOWN
Classifier: Natural Language :: English
Classifier: Programming Language :: Python
Classifier: Topic :: Scientific/Engineering
